venezuela_dollar_price/__init__.py
venezuela_dollar_price/price.py
venezuela_dollar_price-0.1.0.dist-info/LICENSE
venezuela_dollar_price-0.1.0.dist-info/METADATA
venezuela_dollar_price-0.1.0.dist-info/WHEEL
venezuela_dollar_price-0.1.0.dist-info/top_level.txt
venezuela_dollar_price-0.1.0.dist-info/RECORD
