Metadata-Version: 2.1
Name: venezuela-dollar-price
Version: 0.1.0
Summary: A package to get the dollar price in Venezuela
Home-page: https://github.com/Carlososuna11/Venezuela-dollar-price
Author: Carlos Osuna
License: UNKNOWN
Project-URL: Bug Tracker, https://github.com/Carlososuna11/Venezuela-dollar-price/issues
Project-URL: repository, https://github.com/Carlososuna11/Venezuela-dollar-price
Platform: UNKNOWN
Classifier: Programming Language :: Python :: 3
Classifier: License :: OSI Approved :: MIT License
Classifier: Operating System :: OS Independent
Requires-Python: >=3.8
License-File: LICENSE
Requires-Dist: requests
